odkmodel
