Metadata-Version: 1.0
Name: odkmodel
Version: 0.1.2
Summary: SQLAlchemy models for the auto-generated schema by ODKAggregate
Home-page: UNKNOWN
Author: Jeffrey Meyers
Author-email: jeffrey.alan.meyers@gmail.com
License: MIT
Platform: UNKNOWN
